CHANGES.txt
README.txt
bootstrap.py
buildout.cfg
setup.py
src/zope/__init__.py
src/zope.app.sqlscript.egg-info/PKG-INFO
src/zope.app.sqlscript.egg-info/SOURCES.txt
src/zope.app.sqlscript.egg-info/dependency_links.txt
src/zope.app.sqlscript.egg-info/namespace_packages.txt
src/zope.app.sqlscript.egg-info/not-zip-safe
src/zope.app.sqlscript.egg-info/requires.txt
src/zope.app.sqlscript.egg-info/top_level.txt
src/zope/app/__init__.py
src/zope/app/sqlscript/DEPENDENCIES.cfg
src/zope/app/sqlscript/PUBLICATION.cfg
src/zope/app/sqlscript/README.txt
src/zope/app/sqlscript/SETUP.cfg
src/zope/app/sqlscript/__init__.py
src/zope/app/sqlscript/configure.zcml
src/zope/app/sqlscript/dtml.py
src/zope/app/sqlscript/ftesting.zcml
src/zope/app/sqlscript/interfaces.py
src/zope/app/sqlscript/sqlscript-configure.zcml
src/zope/app/sqlscript/sqlscript.py
src/zope/app/sqlscript/testing.py
src/zope/app/sqlscript/browser/__init__.py
src/zope/app/sqlscript/browser/add.pt
src/zope/app/sqlscript/browser/configure.zcml
src/zope/app/sqlscript/browser/edit.pt
src/zope/app/sqlscript/browser/sqlscript.py
src/zope/app/sqlscript/browser/test.pt
src/zope/app/sqlscript/browser/testresults.pt
src/zope/app/sqlscript/browser/tests.py
src/zope/app/sqlscript/tests/__init__.py
src/zope/app/sqlscript/tests/test_arguments.py
src/zope/app/sqlscript/tests/test_sqlscript.py
src/zope/app/sqlscript/tests/testdt_sqlgroup.py
src/zope/app/sqlscript/tests/testdt_sqltest.py
src/zope/app/sqlscript/tests/testdt_sqlvar.py